cliconf/__init__.py
cliconf/arg_store.py
cliconf/command.py
cliconf/command_name.py
cliconf/configure.py
cliconf/dynamic_config.py
cliconf/dynamic_config_name.py
cliconf/ext_inspect.py
cliconf/ext_pyappconf.py
cliconf/ext_typer.py
cliconf/logger.py
cliconf/main.py
cliconf/options.py
cliconf/py_api.py
cliconf/settings.py
cliconf/testing.py
examples/__init__.py
tests/__init__.py
tests/config.py
tests/dirutils.py
tests/ext_click.py
tests/generate.py
tests/test_configure.py
tests/test_main.py
tests/test_python_api.py
tests/fixtures/__init__.py
tests/fixtures/app_settings.py
tests/fixtures/cliconfs.py
tests/fixtures/temp_folder.py
tests/manual/__init__.py
tests/manual/all_optional_json.py
tests/manual/inject_model.py
tests/manual/multi_shared_yaml.py
tests/manual/single_recursive_yaml.py
cliconf-1.0.0a12.dist-info/LICENSE.md
cliconf-1.0.0a12.dist-info/METADATA
cliconf-1.0.0a12.dist-info/WHEEL
cliconf-1.0.0a12.dist-info/top_level.txt
cliconf-1.0.0a12.dist-info/RECORD
