Metadata-Version: 2.1
Name: cliconf
Version: 1.0.0a12
Summary: Framework that lets you write CLIs with Typer that can also be configured via py-app-conf
Home-page: https://github.com/nickderobertis/cliconf
Author: Nick DeRobertis
Author-email: derobertis.nick@gmail.com
License: MIT
Project-URL: Code, https://github.com/nickderobertis/cliconf
Project-URL: Documentation, https://nickderobertis.github.io/cliconf
Classifier: Development Status :: 3 - Alpha
Classifier: Intended Audience :: Developers
Classifier: Programming Language :: Python :: 3.6
Classifier: Programming Language :: Python :: 3.7
License-File: LICENSE.md
Requires-Dist: typer
Requires-Dist: py-app-conf (==1.3.0a10)
Requires-Dist: rich
